h2o_nitro/__init__.py
h2o_nitro/core.py
h2o_nitro/fake.py
h2o_nitro/graphics.py
h2o_nitro/version.py
h2o_nitro-0.21.1.dist-info/LICENSE
h2o_nitro-0.21.1.dist-info/METADATA
h2o_nitro-0.21.1.dist-info/WHEEL
h2o_nitro-0.21.1.dist-info/top_level.txt
h2o_nitro-0.21.1.dist-info/RECORD
