Metadata-Version: 2.1
Name: h2o-nitro
Version: 0.21.1
Summary: Build apps 10x faster. No front-end experience required.
Home-page: https://nitro.h2o.ai/
Author: Prithvi Prabhu
Author-email: prithvi.prabhu@gmail.com
License: UNKNOWN
Project-URL: Documentation, https://nitro.h2o.ai/
Project-URL: Source, https://github.com/h2oai/nitro
Project-URL: Issues, https://github.com/h2oai/nitro/issues
Project-URL: Changelog, https://nitro.h2o.ai/change-log/
Platform: UNKNOWN
Classifier: License :: OSI Approved :: Apache Software License
Classifier: Development Status :: 2 - Pre-Alpha
Classifier: Environment :: Web Environment
Classifier: Intended Audience :: Developers
Classifier: Operating System :: OS Independent
Classifier: Programming Language :: Python :: 3
Classifier: Programming Language :: Python :: 3.7
Classifier: Programming Language :: Python :: 3.8
Classifier: Programming Language :: Python :: 3.9
Classifier: Programming Language :: Python :: 3.10
Classifier: Topic :: Internet :: WWW/HTTP
Classifier: Topic :: Internet :: WWW/HTTP :: Dynamic Content
Classifier: Topic :: Communications :: Chat
Classifier: Topic :: Scientific/Engineering :: Visualization
Classifier: Topic :: Software Development :: Libraries :: Application Frameworks
Classifier: Topic :: Software Development :: Widget Sets
Classifier: Topic :: System :: Distributed Computing
Requires-Python: >=3.7
Provides-Extra: web
Requires-Dist: msgpack >=1.0 ; extra == 'web'
Requires-Dist: h2o-nitro-web ==0.21.1 ; extra == 'web'
